{
    "TD": [
        [
            [
                247.52903225806455,
                1094.8522796352584,
                1607.4653225806453,
                1393.9841945288754
            ]
        ]
    ],
    "TSR": [
        [
            {
                "page": 0,
                "data": [
                    {
                        "bbox": [
                            356.0279373955342,
                            1095.7166141769,
                            456.38516710823586,
                            1129.7992826494262
                        ],
                        "column_nums": [
                            0
                        ],
                        "row_nums": [
                            0
                        ],
                        "column_header": true,
                        "subcell": false,
                        "projected_row_header": false,
                        "cell_text": "PERIOD"
                    },
                    {
                        "bbox": [
                            823.7304985094455,
                            1094.8522796352584,
                            1018.7643600265826,
                            1129.7992826494262
                        ],
                        "column_nums": [
                            1
                        ],
                        "row_nums": [
                            0
                        ],
                        "column_header": true,
                        "subcell": false,
                        "projected_row_header": false,
                        "cell_text": "DESCIPTION"
                    },
                    {
                        "bbox": [
                            1374.74849561126,
                            1094.8522796352584,
                            1509.1893127735584,
                            1126.0123194858122
                        ],
                        "column_nums": [
                            2
                        ],
                        "row_nums": [
                            0
                        ],
                        "column_header": true,
                        "subcell": false,
                        "projected_row_header": false,
                        "cell_text": "AMOUNT"
                    },
                    {
                        "bbox": [
                            247.52903225806455,
                            1168.5300911854104,
                            459.6967741935483,
                            1393.9841945288754
                        ],
                        "column_nums": [
                            0
                        ],
                        "row_nums": [
                            1
                        ],
                        "column_header": false,
                        "subcell": false,
                        "projected_row_header": false,
                        "cell_text": "10/01/01 12/31/01"
                    },
                    {
                        "bbox": [
                            571.6741935483872,
                            1168.5300911854104,
                            1211.1241935483872,
                            1393.9841945288754
                        ],
                        "column_nums": [
                            1
                        ],
                        "row_nums": [
                            1
                        ],
                        "column_header": false,
                        "subcell": false,
                        "projected_row_header": false,
                        "cell_text": "Payment in accordance with terms of the above referenced project between the Florida State University Research Foundation and Philip Morris, under the direction of Dr. Jim Walker. Expenditures for equipment purhcases shall be invoiced in the quarter in which they are purchased."
                    },
                    {
                        "bbox": [
                            1455.7064516129033,
                            1168.5300911854104,
                            1607.4653225806453,
                            1393.9841945288754
                        ],
                        "column_nums": [
                            2
                        ],
                        "row_nums": [
                            1
                        ],
                        "column_header": false,
                        "subcell": false,
                        "projected_row_header": false,
                        "cell_text": "$29,212.99"
                    }
                ]
            }
        ]
    ]
}